{"cursor":"1129","size":15,"audio":[],"currentlang":"en","article":"A 'helitron' is a transposon found in eukaryotes that is thought to replicate by\na rolling-circle mechanism. This category of transposons was discovered by\nVladimir Kapitonov and Jerzy Jurka in 2001.\n","linknr":-1,"url":"Helitron_(biology)","recorded":1376429010,"links":[],"instances":[],"pdf":[],"categories":["Molecular biology","Mobile genetic elements"],"headings":["References"],"image":[],"tags":[],"members":[],"related":["Transposon","Eukaryotes","Vladimir_Kapitonov","Jerzy_Jurka"]}