{"cursor":"15375","size":15,"audio":[],"currentlang":"en","article":"A list of people notable in the field of pathology. \n","linknr":370,"url":"List_of_pathologists","recorded":1376425420,"links":["/w/index.php?title=List_of_pathologists&action=edit","/w/index.php?title=List_of_pathologists&action=edit","//bits.wikimedia.org/favicon/wikipedia.ico","/w/opensearch_desc.php","//en.wikipedia.org/w/api.php?action=rsd","//creativecommons.org/licenses/by-sa/3.0/","/w/index.php?title=Special:RecentChanges&feed=atom","http://en.wikipedia.org/wiki/List_of_pathologists","//bits.wikimedia.org/en.wikipedia.org/load.php?debug=false&lang=en&modules=ext.gadget.DRN-wizard%2CReferenceTooltips%2Ccharinsert%2Cteahouse%7Cext.rtlcite%2Cwikihiero%7Cext.uls.nojs%7Cmediawiki.legacy.commonPrint%2Cshared%7Cmw.PopUpMediaTransform%7Cskins.vector&only=styles&skin=vector&*","//bits.wikimedia.org/en.wikipedia.org/load.php?debug=false&lang=en&modules=ext.visualEditor.viewPageTarget.noscript&only=styles&skin=vector&*","//bits.wikimedia.org/en.wikipedia.org/load.php?debug=false&lang=en&modules=site&only=styles&skin=vector&*","//bits.wikimedia.org/en.wikipedia.org/load.php?debug=false&lang=en&modules=startup&only=scripts&skin=vector&*","//bits.wikimedia.org/geoiplookup","//meta.wikimedia.org","#mw-navigation","#p-search","/wiki/Pathology","#A","#B","#C","#D","#E","#F","#G","#H","#K","#L","#M","#N","#O","#P","#R","#S","#T","#U","#V","#W","#Z","#See_also","/w/index.php?title=List_of_pathologists&action=edit&section=1","/w/index.php?title=List_of_pathologists&veaction=edit&section=1","/wiki/John_Abercrombie_(physician)","/wiki/Maude_Abbott","/wiki/Emile_Achard","/wiki/A._Bernard_Ackerman","/wiki/Lauren_Ackerman","/wiki/Surgical_pathology","/wiki/Theodor_Ackermann","/wiki/Albert_Wojciech_Adamkiewicz","/wiki/Artery_of_Adamkiewicz","/w/index.php?title=W._Stewart_Alexander&action=edit&redlink=1","/wiki/Alexander_disease","/wiki/Friedrich_August_von_Ammon","/wiki/Nikolay_Anichkov","/wiki/Julius_Arnold","/wiki/Ludwig_Aschoff","/wiki/Aschoff_body","/wiki/Atrioventricular_node","/wiki/Max_Askanazy","/wiki/Askanazy_cell","/w/index.php?title=E._Ask-Upmark&action=edit&redlink=1","/wiki/Ask-Upmark_kidney","/w/index.php?title=List_of_pathologists&action=edit&section=2","/w/index.php?title=List_of_pathologists&veaction=edit&section=2","/wiki/Heinrich_von_Bamberger","/wiki/Paul_Clemens_von_Baumgarten","/w/index.php?title=John_Bruce_Beckwith&action=edit&redlink=1","/wiki/Beckwith%E2%80%93Wiedemann_syndrome","/w/index.php?title=Franz_Best&action=edit&redlink=1","/wiki/Vitelliform_macular_dystrophy","/wiki/Marie_Fran%C3%A7ois_Xavier_Bichat","/wiki/Max_Bielschowsky","/wiki/Edmund_Biernacki","/wiki/Erythrocyte_sedimentation_rate","/wiki/Felix_Victor_Birch-Hirschfeld","/wiki/Giulio_Bizzozero","/wiki/Otto_Bollinger","/wiki/William_Boyd_(pathologist)","/wiki/Academic","/wiki/Erich_Franz_Eugen_Bracht","/wiki/Fritz_Brenner","/wiki/Brenner_tumor","/w/index.php?title=Alexander_Breslow&action=edit&redlink=1","/wiki/Breslow%27s_depth","/wiki/Richard_Bright_(physician)","/wiki/Bright%27s_disease","/wiki/Ludwig_von_Buhl","/w/index.php?title=List_of_pathologists&action=edit&section=3","/w/index.php?title=List_of_pathologists&veaction=edit&section=3","/wiki/Santiago_Ram%C3%B3n_y_Cajal","/wiki/Nobel_laureate","/wiki/Francis_Camps","/wiki/Myrtelle_Canavan","/wiki/Canavan_disease","/wiki/Karl_Friedrich_Canstatt","/wiki/Marie_Cassidy","/wiki/Benjamin_Castleman","/wiki/Hans_Chiari","/wiki/Arnold-Chiari_malformation","/wiki/Budd-Chiari_syndrome","/wiki/Jacob_Churg","/wiki/Churg%E2%80%93Strauss_syndrome","/wiki/Giuseppe_Vincenzo_Ciaccio","/wiki/Julius_Friedrich_Cohnheim","/wiki/Astley_Cooper","/wiki/Dominic_Corrigan","/wiki/Corrigan%27s_pulse","/wiki/William_Thomas_Councilman","/wiki/Councilman_body","/wiki/Jean_Cruveilhier","/w/index.php?title=Cruveilhier%27s_sign&action=edit&redlink=1","/wiki/Cruveilhier-Baumgarten_disease","/w/index.php?title=List_of_pathologists&action=edit&section=4","/w/index.php?title=List_of_pathologists&veaction=edit&section=4","/wiki/David_C._Dahlin","/w/index.php?title=James_R._Dawson&action=edit&redlink=1","/wiki/Subacute_sclerosing_panencephalitis","/wiki/Francis_Delafield","/wiki/Franz_Dittrich","/wiki/Karl_Gottfried_Paul_D%C3%B6hle","/wiki/D%C3%B6hle_bodies","/w/index.php?title=William_L._Donohue&action=edit&redlink=1","/wiki/Donohue_syndrome","/wiki/Georges_Dreyer","/wiki/Oxford_University","/w/index.php?title=I._N._Dubin&action=edit&redlink=1","/wiki/Dubin%E2%80%93Johnson_syndrome","/wiki/Cuthbert_Dukes","/wiki/Dukes_classification","/wiki/Guillaume_Dupuytren","/w/index.php?title=List_of_pathologists&action=edit&section=5","/w/index.php?title=List_of_pathologists&veaction=edit&section=5","/wiki/Karl_Joseph_Eberth","/wiki/Paul_Ehrlich","/wiki/Nobel_laureate","/wiki/Jakob_Erdheim","/wiki/Erdheim%E2%80%93Chester_disease","/wiki/James_Ewing_(pathologist)","/wiki/Cornell_University","/wiki/Ewing%27s_sarcoma","/wiki/American_Association_for_Cancer_Research","/w/index.php?title=List_of_pathologists&action=edit&section=6","/w/index.php?title=List_of_pathologists&veaction=edit&section=6","/w/index.php?title=Robert_(Robin)_Sanno_F%C3%A5hr%C3%A6us&action=edit&redlink=1","/wiki/F%C3%A5hr%C3%A6us_effect","/wiki/F%C3%A5hr%C3%A6us%E2%80%93Lindqvist_effect","/wiki/Sidney_Farber","/wiki/Chemotherapy","/wiki/Dana-Farber_Cancer_Institute","/wiki/Martin_J._Fettman","/wiki/Johannes_Andreas_Grib_Fibiger","/wiki/Nobel_laureate","/wiki/Paul_Flechsig","/wiki/Friedrich_Theodor_von_Frerichs","/wiki/Nikolaus_Friedreich","/wiki/August_von_Froriep","/wiki/Robert_Froriep","/w/index.php?title=List_of_pathologists&action=edit&section=7","/w/index.php?title=List_of_pathologists&veaction=edit&section=7","/wiki/Carl_Jakob_Adolf_Christian_Gerhardt","/wiki/Joseph_von_Gerlach","/wiki/Histological_staining","/wiki/Micrography","/wiki/Gustav_Giemsa","/wiki/Giemsa_stain","/wiki/Camillo_Golgi","/wiki/Nobel_laureate","/wiki/Ernest_Goodpasture","/wiki/Goodpasture%27s_syndrome","/wiki/Austin_Gresham","/w/index.php?title=List_of_pathologists&action=edit&section=8","/w/index.php?title=List_of_pathologists&veaction=edit&section=8","/wiki/Hakaru_Hashimoto","/wiki/Ludvig_Hektoen","/wiki/Arnold_Ludwig_Gotthilf_Heller","/wiki/Friedrich_Gustav_Jakob_Henle","/wiki/Richard_L._Heschl","/wiki/Thomas_Hodgkin","/wiki/Hodgkin%27s_lymphoma","/wiki/Friedrich_Albin_Hoffmann","/wiki/Karl_H%C3%BCrthle","/w/index.php?title=List_of_pathologists&action=edit&section=9","/w/index.php?title=List_of_pathologists&veaction=edit&section=9","/wiki/Eduard_Kaufmann","/wiki/Ernest_Kennaway","/wiki/Jack_Kevorkian","/wiki/Edwin_Klebs","/w/index.php?title=Julius_von_Kossa&action=edit&redlink=1","/wiki/Von_Kossa_stain","/wiki/Hans_Kundrat","/w/index.php?title=List_of_pathologists&action=edit&section=10","/w/index.php?title=List_of_pathologists&veaction=edit&section=10","/wiki/Paul_Langerhans","/wiki/William_Boog_Leishman","/wiki/Leishmaniasis","/wiki/George_Lignac","/wiki/James_Linder","/w/index.php?title=List_of_pathologists&action=edit&section=11","/w/index.php?title=List_of_pathologists&veaction=edit&section=11","/wiki/Frank_Burr_Mallory","/wiki/Mallory_body","/wiki/Rod_Markin","/wiki/Alexander_A._Maximow","/wiki/John_McCrae","/wiki/Giovanni_Battista_Morgagni","/wiki/Anatomical_Pathology","/w/index.php?title=List_of_pathologists&action=edit&section=12","/w/index.php?title=List_of_pathologists&veaction=edit&section=12","/wiki/Heijiro_Nakayama","/wiki/Bernhard_Naunyn","/wiki/Franz_Ernst_Christian_Neumann","/wiki/Thomas_Noguchi","/w/index.php?title=List_of_pathologists&action=edit&section=13","/w/index.php?title=List_of_pathologists&veaction=edit&section=13","/wiki/Johannes_Orth","/wiki/William_Osler","/wiki/Johns_Hopkins_Hospital","/w/index.php?title=List_of_pathologists&action=edit&section=14","/w/index.php?title=List_of_pathologists&veaction=edit&section=14","/wiki/Richard_Paltauf","/wiki/George_Nicolas_Papanicolaou","/wiki/Pap_smear","/wiki/Artur_Pappenheim","/wiki/Emil_Ponfick","/w/index.php?title=List_of_pathologists&action=edit&section=15","/w/index.php?title=List_of_pathologists&veaction=edit&section=15","/wiki/Friedrich_Daniel_von_Recklinghausen","/wiki/Benno_Reinhardt","/wiki/Donald_Rix","/wiki/Carl_Freiherr_von_Rokitansky","/wiki/Juan_Rosai","/wiki/Rosai-Dorfman_disease","/wiki/Desmoplastic_small_round_cell_tumor","/wiki/Gustave_Roussy","/w/index.php?title=List_of_pathologists&action=edit&section=16","/w/index.php?title=List_of_pathologists&veaction=edit&section=16","/wiki/Christian_Georg_Schmorl","/wiki/Johann_Lukas_Sch%C3%B6nlein","/wiki/Charles_Scott_Sherrington","/wiki/Nobel_laureate","/wiki/Richard_Shope","/wiki/Maud_Slye","/wiki/Theobald_Smith","/wiki/Sophie_Spitz","/wiki/Spitz_nevus","/w/index.php?title=Edward_Stafne&action=edit&redlink=1","/wiki/Stafne_defect","/w/index.php?title=Allen_Starry&action=edit&redlink=1","/wiki/Warthin%E2%80%93Starry_stain","/wiki/Javier_Arias_Stella","/wiki/Stephen_Sternberg","/wiki/American_Journal_of_Surgical_Pathology","/wiki/Arthur_Purdy_Stout","/wiki/Surgical_pathology","/wiki/Lotte_Strauss","/wiki/Churg%E2%80%93Strauss_syndrome","/w/index.php?title=List_of_pathologists&action=edit&section=17","/w/index.php?title=List_of_pathologists&veaction=edit&section=17","/wiki/Sunao_Tawara","/wiki/Atrioventricular_node","/wiki/Jacques-Ren%C3%A9_Tenon","/wiki/Ludwig_Traube_(physician)","/wiki/V%C3%A1clav_Treitz","/wiki/Charles_Emile_Troisier","/w/index.php?title=List_of_pathologists&action=edit&section=18","/w/index.php?title=List_of_pathologists&veaction=edit&section=18","/wiki/Johann_Paul_Uhle","/wiki/Paul_Gerson_Unna","/wiki/Dermatopathology","/w/index.php?title=List_of_pathologists&action=edit&section=19","/w/index.php?title=List_of_pathologists&veaction=edit&section=19","/w/index.php?title=Jos%C3%A9_Verocay&action=edit&redlink=1","/wiki/Verocay_body","/wiki/Rudolf_Virchow","/w/index.php?title=Adolf_Vossius&action=edit&redlink=1","/wiki/Vossius_ring","/w/index.php?title=List_of_pathologists&action=edit&section=20","/w/index.php?title=List_of_pathologists&veaction=edit&section=20","/wiki/Erik_Waaler","/wiki/Hermann_Julius_Gustav_W%C3%A4chter","/wiki/Bracht-Wachter_bodies","/wiki/Ernst_Leberecht_Wagner","/wiki/Heinrich_Wilhelm_Gottfried_von_Waldeyer-Hartz","/wiki/Robin_Warren","/wiki/Nobel_laureate","/w/index.php?title=Aldred_Warthin&action=edit&redlink=1","/wiki/Warthin%E2%80%93Starry_stain","/wiki/Friedrich_Wegener","/wiki/Wegener%27s_granulomatosis","/wiki/Anton_Weichselbaum","/wiki/Carl_Weigert","/wiki/Adolf_Weil_(physician)","/wiki/Weil%27s_disease","/wiki/Sharon_Weiss","/wiki/Sarcoma","/wiki/William_Henry_Welch","/wiki/Johns_Hopkins_Hospital","/wiki/Max_Westenh%C3%B6fer","/wiki/Rudolf_Virchow","/wiki/Aquatic_ape_hypothesis","/wiki/Chile","/wiki/George_Whipple","/wiki/James_Homer_Wright","/wiki/Wright_stain","/w/index.php?title=List_of_pathologists&action=edit&section=21","/w/index.php?title=List_of_pathologists&veaction=edit&section=21","/wiki/Friedrich_Wilhelm_Zahn","/wiki/Friedrich_Albert_von_Zenker","/wiki/Hugo_Wilhelm_von_Ziemssen","/w/index.php?title=List_of_pathologists&action=edit&section=22","/w/index.php?title=List_of_pathologists&veaction=edit&section=22","/wiki/Pathology","/wiki/List_of_people_by_occupation","//en.wikipedia.org/w/index.php?title=Special:CentralAutoLogin/start&type=1x1&from=enwiki","http://en.wikipedia.org/w/index.php?title=List_of_pathologists&oldid=566524477","/wiki/Help:Category","/wiki/Category:Pathologists","/wiki/Category:Lists_of_health_professionals","/wiki/Category:Lists_of_scientists","/w/index.php?title=Special:UserLogin&returnto=List+of+pathologists&type=signup","/w/index.php?title=Special:UserLogin&returnto=List+of+pathologists","/wiki/List_of_pathologists","/wiki/Talk:List_of_pathologists","#","/wiki/List_of_pathologists","/w/index.php?title=List_of_pathologists&action=edit","/w/index.php?title=List_of_pathologists&veaction=edit","/w/index.php?title=List_of_pathologists&action=history","#","/w/index.php","//bits.wikimedia.org/static-1.22wmf12/skins/vector/images/search-ltr.png?303-4","/wiki/Main_Page","/wiki/Main_Page","/wiki/Portal:Contents","/wiki/Portal:Featured_content","/wiki/Portal:Current_events","/wiki/Special:Random","https://donate.wikimedia.org/wiki/Special:FundraiserRedirector?utm_source=donate&utm_medium=sidebar&utm_campaign=C13_en.wikipedia.org&uselang=en","/wiki/Help:Contents","/wiki/Wikipedia:About","/wiki/Wikipedia:Community_portal","/wiki/Special:RecentChanges","//en.wikipedia.org/wiki/Wikipedia:Contact_us","/wiki/Special:WhatLinksHere/List_of_pathologists","/wiki/Special:RecentChangesLinked/List_of_pathologists","/wiki/Wikipedia:File_Upload_Wizard","/wiki/Special:SpecialPages","/w/index.php?title=List_of_pathologists&oldid=566524477","/w/index.php?title=List_of_pathologists&action=info","//www.wikidata.org/wiki/Q6632067","/w/index.php?title=Special:Cite&page=List_of_pathologists&id=566524477","/w/index.php?title=Special:Book&bookcmd=book_creator&referer=List+of+pathologists","/w/index.php?title=Special:Book&bookcmd=render_article&arttitle=List+of+pathologists&oldid=566524477&writer=rl","/w/index.php?title=List_of_pathologists&printable=yes","#","//www.wikidata.org/wiki/Q6632067#sitelinks-wikipedia","//en.wikipedia.org/wiki/Wikipedia:Text_of_Creative_Commons_Attribution-ShareAlike_3.0_Unported_License","//creativecommons.org/licenses/by-sa/3.0/","//wikimediafoundation.org/wiki/Terms_of_Use","//wikimediafoundation.org/wiki/Privacy_policy","//www.wikimediafoundation.org/","//wikimediafoundation.org/wiki/Privacy_policy","/wiki/Wikipedia:About","/wiki/Wikipedia:General_disclaimer","//en.wikipedia.org/wiki/Wikipedia:Contact_us","//en.m.wikipedia.org/wiki/List_of_pathologists","//wikimediafoundation.org/","//bits.wikimedia.org/images/wikimedia-button.png","//www.mediawiki.org/","//bits.wikimedia.org/static-1.22wmf12/skins/common/images/poweredby_mediawiki_88x31.png","//bits.wikimedia.org/en.wikipedia.org/load.php?debug=false&lang=en&modules=site&only=scripts&skin=vector&*"],"instances":["physician","physician","robin_sanno_fåhræus","physician","pathologist","pathologist","physician"],"pdf":[],"categories":["Pathologists|","Lists of health professionals|Pathologists","Lists of scientists|Pathologists"],"headings":["A","B","C","D","E","F","G","H","K","L","M","N","O","P","R","S","T","U","V","W","Z","See also"],"image":["//en.wikipedia.org/w/index.php?title=Special:CentralAutoLogin/start&type=1x1&from=enwiki","//bits.wikimedia.org/static-1.22wmf12/skins/vector/images/search-ltr.png?303-4","//bits.wikimedia.org/images/wikimedia-button.png","//bits.wikimedia.org/static-1.22wmf12/skins/common/images/poweredby_mediawiki_88x31.png"],"tags":[["john_abercrombie","physician"],["william_boyd","pathologist"],["richard_bright","physician"],["james_ewing","pathologist"],["robert","robin_sanno_fåhræus"],["ludwig_traube","physician"],["adolf_weil","physician"]],"members":["richard_bright","ludwig_traube","robert","adolf_weil","james_ewing","william_boyd","john_abercrombie"],"related":["Pathology","John_Abercrombie_(physician)","Maude_Abbott","Emile_Achard","A._Bernard_Ackerman","Lauren_Ackerman","Surgical_pathology","Theodor_Ackermann","Albert_Wojciech_Adamkiewicz","Artery_of_Adamkiewicz","W._Stewart_Alexander","Alexander_disease","Friedrich_August_von_Ammon","Nikolay_Anichkov","Julius_Arnold","Ludwig_Aschoff","Aschoff_body","Atrioventricular_node","Max_Askanazy","Askanazy_cell","E._Ask-Upmark","Ask-Upmark_kidney","Heinrich_von_Bamberger","Paul_Clemens_von_Baumgarten","John_Bruce_Beckwith","Beckwith–Wiedemann_syndrome","Franz_Best","Vitelliform_macular_dystrophy","Marie_François_Xavier_Bichat","Max_Bielschowsky","Edmund_Biernacki","Erythrocyte_sedimentation_rate","Felix_Victor_Birch-Hirschfeld","Giulio_Bizzozero","Otto_Bollinger","William_Boyd_(pathologist)","Academic","Erich_Franz_Eugen_Bracht","Fritz_Brenner","Brenner_tumor","Alexander_Breslow","Breslow's_depth","Richard_Bright_(physician)","Bright's_disease","Ludwig_von_Buhl","Santiago_Ramón_y_Cajal","Nobel_laureate","Francis_Camps","Myrtelle_Canavan","Canavan_disease","Karl_Friedrich_Canstatt","Marie_Cassidy","Benjamin_Castleman","Hans_Chiari","Arnold-Chiari_malformation","Budd-Chiari_syndrome","Jacob_Churg","Churg–Strauss_syndrome","Giuseppe_Vincenzo_Ciaccio","Julius_Friedrich_Cohnheim","Astley_Cooper","Dominic_Corrigan","Corrigan's_pulse","William_Thomas_Councilman","Councilman_body","Jean_Cruveilhier","Cruveilhier's_sign","Cruveilhier-Baumgarten_disease","David_C._Dahlin","James_R._Dawson","Subacute_sclerosing_panencephalitis","Francis_Delafield","Franz_Dittrich","Karl_Gottfried_Paul_Döhle","Döhle_bodies","William_L._Donohue","Donohue_syndrome","Georges_Dreyer","Oxford_University","I._N._Dubin","Dubin–Johnson_syndrome","Cuthbert_Dukes","Dukes_classification","Guillaume_Dupuytren","Karl_Joseph_Eberth","Paul_Ehrlich","Nobel_laureate","Jakob_Erdheim","Erdheim–Chester_disease","James_Ewing_(pathologist)","Cornell_University","Ewing's_sarcoma","American_Association_for_Cancer_Research","Robert_(Robin)_Sanno_Fåhræus","Fåhræus_effect","Fåhræus–Lindqvist_effect","Sidney_Farber","Chemotherapy","Dana-Farber_Cancer_Institute","Martin_J._Fettman","Johannes_Andreas_Grib_Fibiger","Nobel_laureate","Paul_Flechsig","Friedrich_Theodor_von_Frerichs","Nikolaus_Friedreich","August_von_Froriep","Robert_Froriep","Carl_Jakob_Adolf_Christian_Gerhardt","Joseph_von_Gerlach","Histological_staining","Micrography","Gustav_Giemsa","Giemsa_stain","Camillo_Golgi","Nobel_laureate","Ernest_Goodpasture","Goodpasture's_syndrome","Austin_Gresham","Hakaru_Hashimoto","Ludvig_Hektoen","Arnold_Ludwig_Gotthilf_Heller","Friedrich_Gustav_Jakob_Henle","Richard_L._Heschl","Thomas_Hodgkin","Hodgkin's_lymphoma","Friedrich_Albin_Hoffmann","Karl_Hürthle","Eduard_Kaufmann","Ernest_Kennaway","Jack_Kevorkian","Edwin_Klebs","Julius_von_Kossa","Von_Kossa_stain","Hans_Kundrat","Paul_Langerhans","William_Boog_Leishman","Leishmaniasis","George_Lignac","James_Linder","Frank_Burr_Mallory","Mallory_body","Rod_Markin","Alexander_A._Maximow","John_McCrae","Giovanni_Battista_Morgagni","Anatomical_Pathology","Heijiro_Nakayama","Bernhard_Naunyn","Franz_Ernst_Christian_Neumann","Thomas_Noguchi","Johannes_Orth","William_Osler","Johns_Hopkins_Hospital","Richard_Paltauf","George_Nicolas_Papanicolaou","Pap_smear","Artur_Pappenheim","Emil_Ponfick","Friedrich_Daniel_von_Recklinghausen","Benno_Reinhardt","Donald_Rix","Carl_Freiherr_von_Rokitansky","Juan_Rosai","Rosai-Dorfman_disease","Desmoplastic_small_round_cell_tumor","Gustave_Roussy","Christian_Georg_Schmorl","Johann_Lukas_Schönlein","Charles_Scott_Sherrington","Nobel_laureate","Richard_Shope","Maud_Slye","Theobald_Smith","Sophie_Spitz","Spitz_nevus","Edward_Stafne","Stafne_defect","Allen_Starry","Warthin–Starry_stain","Javier_Arias_Stella","Stephen_Sternberg","American_Journal_of_Surgical_Pathology","Arthur_Purdy_Stout","Surgical_pathology","Lotte_Strauss","Churg–Strauss_syndrome","Sunao_Tawara","Atrioventricular_node","Jacques-René_Tenon","Ludwig_Traube_(physician)","Václav_Treitz","Charles_Emile_Troisier","Johann_Paul_Uhle","Paul_Gerson_Unna","Dermatopathology","José_Verocay","Verocay_body","Rudolf_Virchow","Adolf_Vossius","Vossius_ring","Erik_Waaler","Hermann_Julius_Gustav_Wächter","Bracht-Wachter_bodies","Ernst_Leberecht_Wagner","Heinrich_Wilhelm_Gottfried_von_Waldeyer-Hartz","Robin_Warren","Nobel_laureate","Aldred_Warthin","Warthin–Starry_stain","Friedrich_Wegener","Wegener's_granulomatosis","Anton_Weichselbaum","Carl_Weigert","Adolf_Weil_(physician)","Weil's_disease","Sharon_Weiss","Sarcoma","William_Henry_Welch","Johns_Hopkins_Hospital","Max_Westenhöfer","Rudolf_Virchow","Aquatic_ape_hypothesis","Chile","George_Whipple","James_Homer_Wright","Wright_stain","Friedrich_Wilhelm_Zahn","Friedrich_Albert_von_Zenker","Hugo_Wilhelm_von_Ziemssen","Pathology","List_of_people_by_occupation"]}