{"cursor":"12542","size":15,"audio":[],"currentlang":"en","article":"{{Horseraces infobox |class = Group 1 |horse race = Queen Anne Stakes |image =\n|caption = |location = Ascot Racecourse Ascot, Berkshire, England\n|inaugurated = 1840 |race type = Flat / Thoroughbred |website =\n[http://www.ascot.co.uk/ Ascot] |distance = 1 mile (1,609 metres) |surface =\nTurf |track = Straight |qualification = Four-years-old and up |weight = 9 st 0\nlb 'Allowances' 3 lb for fillies and mares 1 lb for S.\nHemisphere 4yo |purse = Â£350,000 (2013) '1st:'\nÂ£198,485 |bonuses = }} The 'Queen Anne Stakes' is a Group 1 flat horse\nrace in Great Britain open to thoroughbreds aged four years or older. It is run\nat Ascot over a distance of 1 mile (1,609 metres), and it is scheduled to take\nplace each year in June.\n\nThe event was established in 1840, and during the early part of its history it\nwas called the Trial Stakes. It was originally open to horses aged three or\nolder. It was renamed in honour of Queen Anne, the founder of Ascot\nRacecourse, in 1930.\n\nThe Queen Anne Stakes was classed as a Group 3 race in 1971, and it was promoted\nto Group 2 level in 1984. It was given Group 1 status in 2003, and at this point\nthe minimum age of participating horses was raised to four.\n\nIt is now the first race on the opening day of the Royal Ascot meeting.\n","linknr":280,"url":"Queen_Anne_Stakes","recorded":1376418212,"links":["/w/index.php?title=Queen_Anne_Stakes&action=edit","/w/index.php?title=Queen_Anne_Stakes&action=edit","//bits.wikimedia.org/favicon/wikipedia.ico","/w/opensearch_desc.php","//en.wikipedia.org/w/api.php?action=rsd","//creativecommons.org/licenses/by-sa/3.0/","/w/index.php?title=Special:RecentChanges&feed=atom","//bits.wikimedia.org/en.wikipedia.org/load.php?debug=false&lang=en&modules=ext.gadget.DRN-wizard%2CReferenceTooltips%2Ccharinsert%2Cteahouse%7Cext.rtlcite%2Cwikihiero%7Cext.uls.nojs%7Cmediawiki.legacy.commonPrint%2Cshared%7Cmw.PopUpMediaTransform%7Cskins.vector&only=styles&skin=vector&*","//bits.wikimedia.org/en.wikipedia.org/load.php?debug=false&lang=en&modules=site&only=styles&skin=vector&*","//bits.wikimedia.org/en.wikipedia.org/load.php?debug=false&lang=en&modules=startup&only=scripts&skin=vector&*","//bits.wikimedia.org/geoiplookup","//meta.wikimedia.org","#mw-navigation","#p-search","/wiki/Ascot_Racecourse","/wiki/Ascot,_Berkshire","/wiki/Berkshire","/wiki/Flat_racing","/wiki/Thoroughbred","http://www.ascot.co.uk/","/wiki/Stone_(Imperial_mass)","/wiki/Pound_(mass)","/wiki/Filly","/wiki/Mare","/wiki/Southern_Hemisphere","/wiki/Pound_sterling","/wiki/Group_races","/wiki/Flat_racing","/wiki/Horse_racing","/wiki/Great_Britain","/wiki/Thoroughbred","/wiki/Ascot_Racecourse","/wiki/Anne,_Queen_of_Great_Britain","#Records","#Winners_since_1980","#Earlier_winners","#See_also","#References","/w/index.php?title=Queen_Anne_Stakes&action=edit&section=1","/wiki/Jockey","/wiki/Gordon_Richards","/wiki/Frankie_Dettori","/wiki/Horse_trainer","/wiki/Saeed_bin_Suroor","/wiki/Godolphin_Racing","/w/index.php?title=Queen_Anne_Stakes&action=edit&section=2","/wiki/Lester_Piggott","/wiki/Henry_Cecil","/wiki/Daniel_Wildenstein","/wiki/Lester_Piggott","/wiki/Henry_Cecil","/wiki/Pat_Eddery","/wiki/Henry_Cecil","/wiki/Lester_Piggott","/wiki/Henry_Cecil","/wiki/Stavros_Niarchos","/wiki/Greville_Starkey","/wiki/Guy_Harwood","/wiki/Khalid_ibn_Abdullah","/wiki/Pat_Eddery","/wiki/Jeremy_Tree","/wiki/Ray_Cochrane","/wiki/Luca_Cumani","/wiki/Michael_Roberts_(jockey)","/wiki/Hamdan_bin_Rashid_Al_Maktoum","/wiki/Warning_(horse)","/wiki/Pat_Eddery","/wiki/Guy_Harwood","/wiki/Khalid_ibn_Abdullah","/wiki/Frankie_Dettori","/wiki/Luca_Cumani","/wiki/Michael_Roberts_(jockey)","/wiki/Clive_Brittain","/wiki/Luciano_Gaucci","/wiki/Willie_Carson","/wiki/John_L._Dunlop","/wiki/Hamdan_bin_Rashid_Al_Maktoum","/wiki/Michael_Kinane","/wiki/Clive_Brittain","/wiki/Barathea_(horse)","/wiki/Michael_Kinane","/wiki/Luca_Cumani","/wiki/Mohammed_bin_Rashid_Al_Maktoum","/wiki/Michael_Hills_(jockey)","/wiki/Geoff_Wragg","/wiki/Michael_Kinane","/wiki/Saeed_bin_Suroor","/wiki/Godolphin_Racing","/wiki/Frankie_Dettori","/wiki/Saeed_bin_Suroor","/wiki/Godolphin_Racing","/wiki/Intikhab","/wiki/Frankie_Dettori","/wiki/Saeed_bin_Suroor","/wiki/Godolphin_Racing","/wiki/Cape_Cross_(horse)","/wiki/Gary_L._Stevens","/wiki/Saeed_bin_Suroor","/wiki/Godolphin_Racing","/wiki/Kalanisi","/wiki/Kieren_Fallon","/wiki/Michael_Stoute","/wiki/Aga_Khan_IV","/wiki/Medicean_(horse)","/wiki/Kieren_Fallon","/wiki/Michael_Stoute","/wiki/Johnny_Murtagh","/wiki/Michael_Stoute","/wiki/Maktoum_bin_Rashid_Al_Maktoum","/wiki/Frankie_Dettori","/wiki/Saeed_bin_Suroor","/wiki/Godolphin_Racing","/wiki/Refuse_To_Bend","/wiki/Frankie_Dettori","/wiki/Saeed_bin_Suroor","/wiki/Godolphin_Racing","#endnote_2005a","/wiki/Christophe_Soumillon","/wiki/Andr%C3%A9_Fabre","/wiki/Aga_Khan_IV","/wiki/Ad_Valorem_(horse)","/wiki/Kieren_Fallon","/wiki/Aidan_O%27Brien","/wiki/Sue_Magnier","/wiki/Ramonti","/wiki/Frankie_Dettori","/wiki/Saeed_bin_Suroor","/wiki/Godolphin_Racing","/wiki/Haradasun","/wiki/Johnny_Murtagh","/wiki/Aidan_O%27Brien","/wiki/Sue_Magnier","/wiki/Paco_Boy","/wiki/Richard_Hughes_(jockey)","/wiki/Richard_Hannon","/wiki/Goldikova","/wiki/Olivier_Peslier","/wiki/Freddy_Head","/wiki/Wertheimer_et_Fr%C3%A8re","/wiki/Canford_Cliffs_(horse)","/wiki/Richard_Hughes_(jockey)","/wiki/Richard_Hannon","/wiki/Michael_Tabor","/wiki/Frankel_(horse)","/wiki/Tom_Queally","/wiki/Henry_Cecil","/wiki/Khalid_ibn_Abdullah","/wiki/Joseph_O%27Brien_(jockey)","/wiki/Aidan_O%27Brien","/wiki/Sue_Magnier","/wiki/Michael_Tabor","#ref_2005a","/wiki/York_Racecourse","/w/index.php?title=Queen_Anne_Stakes&action=edit&section=3","/wiki/Whisk_Broom_II","/wiki/Comrade_(horse)","/wiki/Fair_Trial","/wiki/Royal_Charger","/w/index.php?title=Queen_Anne_Stakes&action=edit&section=4","/wiki/Horseracing_in_Great_Britain","/wiki/List_of_British_flat_horse_races","/wiki/Category:Recurring_sporting_events_established_in_1840","/w/index.php?title=Queen_Anne_Stakes&action=edit&section=5","/wiki/Racing_Post","http://www.racingpost.com/horses/result_home.sd?race_id=91345&r_date=1988-06-14","http://www.racingpost.com/horses/result_home.sd?race_id=95580&r_date=1989-06-20","http://www.racingpost.com/horses/result_home.sd?race_id=100062&r_date=1990-06-19","http://www.racingpost.com/horses/result_home.sd?race_id=104857&r_date=1991-06-18","http://www.racingpost.com/horses/result_home.sd?race_id=109610&r_date=1992-06-16","http://www.racingpost.com/horses/result_home.sd?race_id=114629&r_date=1993-06-15","http://www.racingpost.com/horses/result_home.sd?race_id=119756&r_date=1994-06-14","http://www.racingpost.com/horses/result_home.sd?race_id=125285&r_date=1995-06-20","http://www.racingpost.com/horses/result_home.sd?race_id=202109&r_date=1996-06-18","http://www.racingpost.com/horses/result_home.sd?race_id=237434&r_date=1997-06-17","http://www.racingpost.com/horses/result_home.sd?race_id=250762&r_date=1998-06-16","http://www.racingpost.com/horses/result_home.sd?race_id=265955&r_date=1999-06-15","http://www.racingpost.com/horses/result_home.sd?race_id=280064&r_date=2000-06-20","http://www.racingpost.com/horses/result_home.sd?race_id=299859&r_date=2001-06-19","http://www.racingpost.com/horses/result_home.sd?race_id=315308&r_date=2002-06-18","http://www.racingpost.com/horses/result_home.sd?race_id=330970&r_date=2003-06-17","http://www.racingpost.com/horses/result_home.sd?race_id=349236&r_date=2004-06-15","http://www.racingpost.com/horses/result_home.sd?race_id=381946&r_date=2005-06-14","http://www.racingpost.com/horses/result_home.sd?race_id=405933&r_date=2006-06-20","http://www.racingpost.com/horses/result_home.sd?race_id=429753&r_date=2007-06-19","http://www.racingpost.com/horses/result_home.sd?race_id=454532&r_date=2008-06-17","http://www.racingpost.com/horses/result_home.sd?race_id=479596&r_date=2009-06-16","http://www.racingpost.com/horses/result_home.sd?race_id=503540&r_date=2010-06-15","http://www.racingpost.com/horses/result_home.sd?race_id=528247&r_date=2011-06-14","http://www.racingpost.com/horses/result_home.sd?race_id=552341&r_date=2012-06-19","http://www.racingpost.com/horses/result_home.sd?race_id=576289&r_date=2013-06-18","http://www.galopp-sieger.de/galoppsieger/sieger?rennkz=EAsQuAnS&backlink=1","http://www.horseracingintfed.com/racingDisplay.asp?section=8&racepid=52337","http://www.pedigreequery.com/index.php?search_bar=stakes&query_type=stakes&field=view&id=673","http://www.pedigreequery.com/index.php?search_bar=stakes&query_type=stakes&field=view&id=8180","/wiki/International_Standard_Book_Number","/wiki/Special:BookSources/1-873626-15-0","/wiki/Template:Royal_Ascot","/wiki/Template_talk:Royal_Ascot","//en.wikipedia.org/w/index.php?title=Template:Royal_Ascot&action=edit","/wiki/Royal_Ascot","/wiki/King%27s_Stand_Stakes","/wiki/St._James%27s_Palace_Stakes","/wiki/Coventry_Stakes","/wiki/Jersey_Stakes","/wiki/Duke_of_Cambridge_Stakes","/wiki/Prince_of_Wales%27s_Stakes","/wiki/Royal_Hunt_Cup","/wiki/Queen_Mary_Stakes","/wiki/Norfolk_Stakes_(Great_Britain)","/wiki/Ribblesdale_Stakes","/wiki/Ascot_Gold_Cup","/wiki/Tercentenary_Stakes","/wiki/Albany_Stakes_(Great_Britain)","/wiki/King_Edward_VII_Stakes","/wiki/Coronation_Stakes","/wiki/Wolferton_Handicap","/wiki/Queen%27s_Vase","/wiki/Hardwicke_Stakes","/wiki/Diamond_Jubilee_Stakes","/wiki/Wokingham_Stakes","/wiki/Duke_of_Edinburgh_Stakes","/wiki/Queen_Alexandra_Stakes","//en.wikipedia.org/w/index.php?title=Special:CentralAutoLogin/start&type=1x1&from=enwiki","http://en.wikipedia.org/w/index.php?title=Queen_Anne_Stakes&oldid=566334837","/wiki/Help:Categories","/wiki/Category:Flat_races_in_Great_Britain","/wiki/Category:Ascot_Racecourse","/wiki/Category:Open_mile_category_horse_races","/w/index.php?title=Special:UserLogin&returnto=Queen+Anne+Stakes&type=signup","/w/index.php?title=Special:UserLogin&returnto=Queen+Anne+Stakes","/wiki/Queen_Anne_Stakes","/wiki/Talk:Queen_Anne_Stakes","#","/wiki/Queen_Anne_Stakes","/w/index.php?title=Queen_Anne_Stakes&action=edit","/w/index.php?title=Queen_Anne_Stakes&action=history","#","/w/index.php","//bits.wikimedia.org/static-1.22wmf11/skins/vector/images/search-ltr.png?303-4","/wiki/Main_Page","/wiki/Main_Page","/wiki/Portal:Contents","/wiki/Portal:Featured_content","/wiki/Portal:Current_events","/wiki/Special:Random","//donate.wikimedia.org/wiki/Special:FundraiserRedirector?utm_source=donate&utm_medium=sidebar&utm_campaign=C13_en.wikipedia.org&uselang=en","/wiki/Help:Contents","/wiki/Wikipedia:About","/wiki/Wikipedia:Community_portal","/wiki/Special:RecentChanges","//en.wikipedia.org/wiki/Wikipedia:Contact_us","/wiki/Special:WhatLinksHere/Queen_Anne_Stakes","/wiki/Special:RecentChangesLinked/Queen_Anne_Stakes","/wiki/Wikipedia:File_Upload_Wizard","/wiki/Special:SpecialPages","/w/index.php?title=Queen_Anne_Stakes&oldid=566334837","/w/index.php?title=Queen_Anne_Stakes&action=info","//www.wikidata.org/wiki/Q3414002","/w/index.php?title=Special:Cite&page=Queen_Anne_Stakes&id=566334837","/w/index.php?title=Special:Book&bookcmd=book_creator&referer=Queen+Anne+Stakes","/w/index.php?title=Special:Book&bookcmd=render_article&arttitle=Queen+Anne+Stakes&oldid=566334837&writer=rl","/w/index.php?title=Queen_Anne_Stakes&printable=yes","//fr.wikipedia.org/wiki/Queen_Anne_Stakes","//ja.wikipedia.org/wiki/%E3%82%AF%E3%82%A4%E3%83%BC%E3%83%B3%E3%82%A2%E3%83%B3%E3%82%B9%E3%83%86%E3%83%BC%E3%82%AF%E3%82%B9","#","//www.wikidata.org/wiki/Q3414002#sitelinks-wikipedia","//en.wikipedia.org/wiki/Wikipedia:Text_of_Creative_Commons_Attribution-ShareAlike_3.0_Unported_License","//creativecommons.org/licenses/by-sa/3.0/","//wikimediafoundation.org/wiki/Terms_of_Use","//wikimediafoundation.org/wiki/Privacy_policy","//www.wikimediafoundation.org/","//wikimediafoundation.org/wiki/Privacy_policy","/wiki/Wikipedia:About","/wiki/Wikipedia:General_disclaimer","//en.wikipedia.org/wiki/Wikipedia:Contact_us","//en.m.wikipedia.org/wiki/Queen_Anne_Stakes","//wikimediafoundation.org/","//bits.wikimedia.org/images/wikimedia-button.png","//www.mediawiki.org/","//bits.wikimedia.org/static-1.22wmf11/skins/common/images/poweredby_mediawiki_88x31.png","//bits.wikimedia.org/en.wikipedia.org/load.php?debug=false&lang=en&modules=site&only=scripts&skin=vector&*"],"instances":["horse","jockey","horse","horse","imperial_mass","horse","horse","jockey","jockey","mass","horse","jockey","horse","horse"],"pdf":[],"categories":["Flat races in Great Britain","Ascot Racecourse","Open mile category horse races"],"headings":["Records","Winners since 1980","Earlier winners","See also","References"],"image":["//en.wikipedia.org/w/index.php?title=Special:CentralAutoLogin/start&type=1x1&from=enwiki","//bits.wikimedia.org/static-1.22wmf11/skins/vector/images/search-ltr.png?303-4","//bits.wikimedia.org/images/wikimedia-button.png","//bits.wikimedia.org/static-1.22wmf11/skins/common/images/poweredby_mediawiki_88x31.png"],"tags":[["stone","imperial_mass"],["pound","mass"],["michael_roberts","jockey"],["warning","horse"],["michael_roberts","jockey"],["barathea","horse"],["michael_hills","jockey"],["cape_cross","horse"],["medicean","horse"],["ad_valorem","horse"],["richard_hughes","jockey"],["canford_cliffs","horse"],["richard_hughes","jockey"],["frankel","horse"],["joseph_o'brien","jockey"],["comrade","horse"]],"members":["cape_cross","michael_hills","comrade","ad_valorem","stone","barathea","frankel","michael_roberts","richard_hughes","pound","warning","canford_cliffs","medicean"],"related":["Ascot_Racecourse","Ascot,_Berkshire","Berkshire","Flat_racing","Thoroughbred","Stone_(Imperial_mass)","Pound_(mass)","Filly","Mare","Southern_Hemisphere","Pound_sterling","Group_races","Flat_racing","Horse_racing","Great_Britain","Thoroughbred","Ascot_Racecourse","Anne,_Queen_of_Great_Britain","Gordon_Richards","Frankie_Dettori","Saeed_bin_Suroor","Godolphin_Racing","Lester_Piggott","Henry_Cecil","Daniel_Wildenstein","Lester_Piggott","Henry_Cecil","Pat_Eddery","Henry_Cecil","Lester_Piggott","Henry_Cecil","Stavros_Niarchos","Greville_Starkey","Guy_Harwood","Khalid_ibn_Abdullah","Pat_Eddery","Jeremy_Tree","Ray_Cochrane","Luca_Cumani","Michael_Roberts_(jockey)","Hamdan_bin_Rashid_Al_Maktoum","Warning_(horse)","Pat_Eddery","Guy_Harwood","Khalid_ibn_Abdullah","Frankie_Dettori","Luca_Cumani","Michael_Roberts_(jockey)","Clive_Brittain","Luciano_Gaucci","Willie_Carson","John_L._Dunlop","Hamdan_bin_Rashid_Al_Maktoum","Michael_Kinane","Clive_Brittain","Barathea_(horse)","Michael_Kinane","Luca_Cumani","Mohammed_bin_Rashid_Al_Maktoum","Michael_Hills_(jockey)","Geoff_Wragg","Michael_Kinane","Saeed_bin_Suroor","Godolphin_Racing","Frankie_Dettori","Saeed_bin_Suroor","Godolphin_Racing","Intikhab","Frankie_Dettori","Saeed_bin_Suroor","Godolphin_Racing","Cape_Cross_(horse)","Gary_L._Stevens","Saeed_bin_Suroor","Godolphin_Racing","Kalanisi","Kieren_Fallon","Michael_Stoute","Aga_Khan_IV","Medicean_(horse)","Kieren_Fallon","Michael_Stoute","Johnny_Murtagh","Michael_Stoute","Maktoum_bin_Rashid_Al_Maktoum","Frankie_Dettori","Saeed_bin_Suroor","Godolphin_Racing","Refuse_To_Bend","Frankie_Dettori","Saeed_bin_Suroor","Godolphin_Racing","Christophe_Soumillon","André_Fabre","Aga_Khan_IV","Ad_Valorem_(horse)","Kieren_Fallon","Aidan_O'Brien","Sue_Magnier","Ramonti","Frankie_Dettori","Saeed_bin_Suroor","Godolphin_Racing","Haradasun","Johnny_Murtagh","Aidan_O'Brien","Sue_Magnier","Paco_Boy","Richard_Hughes_(jockey)","Richard_Hannon","Goldikova","Olivier_Peslier","Freddy_Head","Wertheimer_et_Frère","Canford_Cliffs_(horse)","Richard_Hughes_(jockey)","Richard_Hannon","Michael_Tabor","Frankel_(horse)","Tom_Queally","Henry_Cecil","Khalid_ibn_Abdullah","Joseph_O'Brien_(jockey)","Aidan_O'Brien","Sue_Magnier","Michael_Tabor","York_Racecourse","Whisk_Broom_II","Comrade_(horse)","Fair_Trial","Royal_Charger","Horseracing_in_Great_Britain","List_of_British_flat_horse_races","Racing_Post"]}