{"cursor":"14221","size":15,"audio":[],"currentlang":"en","article":"\n'Woodchips' are a medium-sized solid material made by cutting, or chipping,\nlarger pieces of wood. Woodchips may be used as a biomass solid fuel and are raw\nmaterial for producing wood pulp. They may also be used as an organic mulch in\ngardening, landscaping, restoration ecology and mushroom cultivation. According\nto the different chemical and mechanical properties of the masses, the wood logs\nare mostly peeled, and the bark chips and the woodchips processed in different\nprocesses. The process of making wood chips are called woodchipping and are done\nwith a woodchipper.\n","linknr":-1,"url":"woodchips","recorded":1376428018,"links":[],"instances":["gravity","paper"],"pdf":[],"categories":["Sustainable products","Soil improvers","Biomass","Wood fuel"],"headings":["Raw materials","Production","Applications","Environmental Issues","Market Products, Supply and Demand","See also","References","External links"],"image":[],"tags":[["pulp","paper"],["chute","gravity"]],"members":["chute","pulp"],"related":["Wood","Biomass","Solid_fuel","Wood_pulp","Mulch","Gardening","Landscaping","Restoration_ecology","Mushroom","Woodchipper","Pulpwood","Plantations","Construction","Agriculture","Landscaping","Logging","Sawmill","Energy_crops","Woodchipper","Pulp_(paper)","Pneumatic","Conveyor_belt","Chute_(gravity)","Pulp_mill","Mulch","Water_conservation","Soil_erosion","Acorn","Habitat","Ecological_restoration","Ramial_chipped_wood","Mulch","Playground_surfacing","Electric_power","Renewable_energy","Coal_power_plant","Steam_turbine","Heat_engine","Coal","Biomass","Energy_crisis","Climate_change","Carbon_neutral","Sustainable","Wood_ash","Fertilizer","Biochar","Wood_pellets","Steam_engines","Stirling_engines","Otto_engines","Woodgas","Internal_combustion_engines","Gasification","Woodgas","Sustainable","Renewable_energy","Clear_cutting","Forest","Ecosystem","Solar_energy","Short_rotation_coppice","Bulking_agent","Industrial_composting","Biodegradeable","Biosolids","Firebreak","Wildfire","Biofuels","Barkdust","Renewable_heat","Woodchipping_in_Australia"]}